odoo/addons/web_domain_field/README.rst
odoo/addons/web_domain_field/__init__.py
odoo/addons/web_domain_field/__manifest__.py
odoo/addons/web_domain_field/i18n/it.po
odoo/addons/web_domain_field/i18n/web_domain_field.pot
odoo/addons/web_domain_field/readme/CONTRIBUTORS.rst
odoo/addons/web_domain_field/readme/DESCRIPTION.rst
odoo/addons/web_domain_field/readme/USAGE.rst
odoo/addons/web_domain_field/static/description/icon.png
odoo/addons/web_domain_field/static/description/index.html
odoo/addons/web_domain_field/static/lib/js/pyeval.js
odoo/addons/web_domain_field/static/tests/test_qunit.js
odoo/addons/web_domain_field/tests/__init__.py
odoo/addons/web_domain_field/tests/test_qunit.py
odoo_addon_web_domain_field-16.0.1.0.1.2.dist-info/METADATA
odoo_addon_web_domain_field-16.0.1.0.1.2.dist-info/WHEEL
odoo_addon_web_domain_field-16.0.1.0.1.2.dist-info/top_level.txt
odoo_addon_web_domain_field-16.0.1.0.1.2.dist-info/RECORD
